qrest/__init__.py
qrest/conf.py
qrest/exception.py
qrest/module_class_registry.py
qrest/resource.py
qrest/response.py
qrest/utils.py
qrest/auth/__init__.py
qrest/auth/cas.py
qrest-4.2.2.dist-info/licenses/LICENSE
qrest-4.2.2.dist-info/METADATA
qrest-4.2.2.dist-info/WHEEL
qrest-4.2.2.dist-info/top_level.txt
qrest-4.2.2.dist-info/RECORD
