Metadata-Version: 2.4
Name: qrest
Version: 4.2.2
Summary: A generic python REST client
Home-page: https://github.com/JorisBenschop/qrest
Author: Joris Benschop
Author-email: joris@digital-engines.nl
Maintainer: Joris Benschop
Maintainer-email: joris@digital-engines.nl
License: GPLv3
Keywords: generic REST API client
Classifier: Development Status :: 5 - Production/Stable
Classifier: Intended Audience :: Information Technology
Classifier: Topic :: Software Development :: Libraries :: Python Modules
Classifier: License :: OSI Approved :: GNU General Public License v3 (GPLv3)
Classifier: Programming Language :: Python :: 3
Classifier: Programming Language :: Python :: 3.9
Classifier: Programming Language :: Python :: 3.10
Classifier: Programming Language :: Python :: 3.11
Classifier: Programming Language :: Python :: 3.12
Classifier: Programming Language :: Python :: 3.13
Requires-Python: ~=3.6
License-File: LICENSE
Requires-Dist: requests
Requires-Dist: uritools
Requires-Dist: jsonschema
Provides-Extra: dev
Requires-Dist: Sphinx; extra == "dev"
Provides-Extra: test
Requires-Dist: requests-mock; extra == "test"
Dynamic: author
Dynamic: author-email
Dynamic: classifier
Dynamic: description
Dynamic: home-page
Dynamic: keywords
Dynamic: license
Dynamic: license-file
Dynamic: maintainer
Dynamic: maintainer-email
Dynamic: provides-extra
Dynamic: requires-dist
Dynamic: requires-python
Dynamic: summary
